{"files":{"packages/cache/dist/index.js.map":{"size":257,"mtime_nanos":1776473404040480649,"mode":420,"is_dir":false},"packages/cache/dist/gateway-binder.d.ts":{"size":418,"mtime_nanos":1776473407498242840,"mode":420,"is_dir":false},"packages/cache/dist/base-cache.d.ts.map":{"size":412,"mtime_nanos":1776473407490402258,"mode":420,"is_dir":false},"packages/cache/dist/cache-manager.js":{"size":1256,"mtime_nanos":1776473403984181277,"mode":420,"is_dir":false},"packages/cache/dist/cache-manager.js.map":{"size":3227,"mtime_nanos":1776473403984140944,"mode":420,"is_dir":false},"packages/cache/dist/cache-manager.d.ts.map":{"size":1039,"mtime_nanos":1776473407495551577,"mode":420,"is_dir":false},"packages/cache/dist/index.d.ts.map":{"size":171,"mtime_nanos":1776473407498966719,"mode":420,"is_dir":false},"packages/cache/dist/gateway-binder.js.map":{"size":7418,"mtime_nanos":1776473404049083777,"mode":420,"is_dir":false},"packages/cache/.turbo/turbo-build.log":{"size":289,"mtime_nanos":1776473407518779487,"mode":420,"is_dir":false},"packages/cache/dist/index.d.ts":{"size":141,"mtime_nanos":1776473407499162262,"mode":420,"is_dir":false},"packages/cache/dist/base-cache.js.map":{"size":1185,"mtime_nanos":1776473404043553373,"mode":420,"is_dir":false},"packages/cache/dist/base-cache.js":{"size":516,"mtime_nanos":1776473404043581332,"mode":420,"is_dir":false},"packages/cache/dist/gateway-binder.d.ts.map":{"size":512,"mtime_nanos":1776473407498023672,"mode":420,"is_dir":false},"packages/cache/dist/base-cache.d.ts":{"size":310,"mtime_nanos":1776473407492073350,"mode":420,"is_dir":false},"packages/cache/dist/cache-manager.d.ts":{"size":918,"mtime_nanos":1776473407495990996,"mode":420,"is_dir":false},"packages/cache/dist/gateway-binder.js":{"size":3522,"mtime_nanos":1776473404049118194,"mode":420,"is_dir":false},"packages/cache/dist":{"size":0,"mtime_nanos":0,"mode":0,"is_dir":true},"packages/cache/dist/index.js":{"size":140,"mtime_nanos":1776473404041145861,"mode":420,"is_dir":false}},"order":["packages/cache/.turbo/turbo-build.log","packages/cache/dist","packages/cache/dist/base-cache.d.ts","packages/cache/dist/base-cache.d.ts.map","packages/cache/dist/base-cache.js","packages/cache/dist/base-cache.js.map","packages/cache/dist/cache-manager.d.ts","packages/cache/dist/cache-manager.d.ts.map","packages/cache/dist/cache-manager.js","packages/cache/dist/cache-manager.js.map","packages/cache/dist/gateway-binder.d.ts","packages/cache/dist/gateway-binder.d.ts.map","packages/cache/dist/gateway-binder.js","packages/cache/dist/gateway-binder.js.map","packages/cache/dist/index.d.ts","packages/cache/dist/index.d.ts.map","packages/cache/dist/index.js","packages/cache/dist/index.js.map"]}